rtl/signed_adder.v
`timescale 1ns/1ps

module signed_adder #(
    parameter W = 6
)(
    input  wire signed [W-1:0] a,
    input  wire signed [W-1:0] b,
    output wire signed [W:0]   y
);

    wire signed [W:0] a_ext;
    wire signed [W:0] b_ext;

    assign a_ext = {a[W-1], a};
    assign b_ext = {b[W-1], b};

    assign y = a_ext + b_ext;

endmodule

tb/tb_signed_adder.v
`timescale 1ns/1ps

module tb_signed_adder;

    localparam W = 6;
    localparam MIN_VAL = -(1 << (W-1));
    localparam MAX_VAL =  (1 << (W-1)) - 1;

    reg  signed [W-1:0] a;
    reg  signed [W-1:0] b;
    wire signed [W:0]   y;

    reg  signed [W:0] expected;

    integer ia;
    integer ib;
    integer error_count;
    integer test_count;

    signed_adder #(
        .W(W)
    ) dut (
        .a(a),
        .b(b),
        .y(y)
    );

    task check_output;
        begin
            if (y !== expected) begin
                $display("FAIL: a=%0d, b=%0d, expected=%0d, got=%0d",
                         a, b, expected, y);
                error_count = error_count + 1;
            end
            test_count = test_count + 1;
        end
    endtask

    initial begin
        $dumpfile("sim/waveforms/signed_adder.vcd");
        $dumpvars(0, tb_signed_adder);

        error_count = 0;
        test_count  = 0;

        // Exhaustive test for all possible W-bit signed inputs
        for (ia = MIN_VAL; ia <= MAX_VAL; ia = ia + 1) begin
            for (ib = MIN_VAL; ib <= MAX_VAL; ib = ib + 1) begin
                a = ia;
                b = ib;
                expected = ia + ib;
                #1;
                check_output();
            end
        end

        $display("====================================");
        $display("Total tests  = %0d", test_count);
        $display("Total errors = %0d", error_count);

        if (error_count == 0) begin
            $display("ALL TESTS PASSED.");
        end else begin
            $display("TEST FAILED.");
        end
        $display("====================================");

        $finish;
    end

endmodule

sim/waveforms/signed_adder.vcd
$date
	Sat May  2 15:20:58 2026
$end
$version
	Icarus Verilog
$end
$timescale
	1ps
$end
$scope module tb_signed_adder $end
$var wire 7 ! y [6:0] $end
$var parameter 38 " MAX_VAL $end
$var parameter 37 # MIN_VAL $end
$var parameter 32 $ W $end
$var reg 6 % a [5:0] $end
$var reg 6 & b [5:0] $end
$var reg 7 ' expected [6:0] $end
$var integer 32 ( error_count [31:0] $end
$var integer 32 ) ia [31:0] $end
$var integer 32 * ib [31:0] $end
$var integer 32 + test_count [31:0] $end
$scope module dut $end
$var wire 6 , a [5:0] $end
$var wire 6 - b [5:0] $end
$var wire 7 . y [6:0] $end
$var wire 7 / b_ext [6:0] $end
$var wire 7 0 a_ext [6:0] $end
$var parameter 32 1 W $end
$upscope $end
$scope task check_output $end
$upscope $end
$upscope $end
$enddefinitions $end
$comment Show the parameter values. $end
$dumpall
b110 1
b110 $
b1111111111111111111111111111111100000 #
b11111 "
$end
#0
$dumpvars
b1100000 0
b1100000 /
b1000000 .
b100000 -
b100000 ,
b0 +
b11111111111111111111111111100000 *
b11111111111111111111111111100000 )
b0 (
b1000000 '
b100000 &
b100000 %
b1000000 !
$end
#1000
b1000001 '
b1000001 !
b1000001 .
b1100001 /
b100001 &
b100001 -
b11111111111111111111111111100001 *
b1 +
#2000
b1000010 '
b1000010 !
b1000010 .
b1100010 /
b100010 &
b100010 -
b11111111111111111111111111100010 *
b10 +
#3000
b1000011 '
b1000011 !
b1000011 .
b1100011 /
b100011 &
b100011 -
b11111111111111111111111111100011 *
b11 +
#4000
b1000100 '
b1000100 !
b1000100 .
b1100100 /
b100100 &
b100100 -
b11111111111111111111111111100100 *
b100 +
#5000
b1000101 '
b1000101 !
b1000101 .
b1100101 /
b100101 &
b100101 -
b11111111111111111111111111100101 *
b101 +
#6000
b1000110 '
b1000110 !
b1000110 .
b1100110 /
b100110 &
b100110 -
b11111111111111111111111111100110 *
b110 +
#7000
b1000111 '
b1000111 !
b1000111 .
b1100111 /
b100111 &
b100111 -
b11111111111111111111111111100111 *
b111 +
#8000
b1001000 '
b1001000 !
b1001000 .
b1101000 /
b101000 &
b101000 -
b11111111111111111111111111101000 *
b1000 +
#9000
b1001001 '
b1001001 !
b1001001 .
b1101001 /
b101001 &
b101001 -
b11111111111111111111111111101001 *
b1001 +
#10000
b1001010 '
b1001010 !
b1001010 .
b1101010 /
b101010 &
b101010 -
b11111111111111111111111111101010 *
b1010 +
#11000
b1001011 '
b1001011 !
b1001011 .
b1101011 /
b101011 &
b101011 -
b11111111111111111111111111101011 *
b1011 +
#12000
b1001100 '
b1001100 !
b1001100 .
b1101100 /
b101100 &
b101100 -
b11111111111111111111111111101100 *
b1100 +
#13000
b1001101 '
b1001101 !
b1001101 .
b1101101 /
b101101 &
b101101 -
b11111111111111111111111111101101 *
b1101 +
#14000
b1001110 '
b1001110 !
b1001110 .
b1101110 /
b101110 &
b101110 -
b11111111111111111111111111101110 *
b1110 +
#15000
b1001111 '
b1001111 !
b1001111 .
b1101111 /
b101111 &
b101111 -
b11111111111111111111111111101111 *
b1111 +
#16000
b1010000 '
b1010000 !
b1010000 .
b1110000 /
b110000 &
b110000 -
b11111111111111111111111111110000 *
b10000 +
#17000
b1010001 '
b1010001 !
b1010001 .
b1110001 /
b110001 &
b110001 -
b11111111111111111111111111110001 *
b10001 +
#18000
b1010010 '
b1010010 !
b1010010 .
b1110010 /
b110010 &
b110010 -
b11111111111111111111111111110010 *
b10010 +
#19000
b1010011 '
b1010011 !
b1010011 .
b1110011 /
b110011 &
b110011 -
b11111111111111111111111111110011 *
b10011 +
#20000
b1010100 '
b1010100 !
b1010100 .
b1110100 /
b110100 &
b110100 -
b11111111111111111111111111110100 *
b10100 +
#21000
b1010101 '
b1010101 !
b1010101 .
b1110101 /
b110101 &
b110101 -
b11111111111111111111111111110101 *
b10101 +
#22000
b1010110 '
b1010110 !
b1010110 .
b1110110 /
b110110 &
b110110 -
b11111111111111111111111111110110 *
b10110 +
#23000
b1010111 '
b1010111 !
b1010111 .
b1110111 /
b110111 &
b110111 -
b11111111111111111111111111110111 *
b10111 +
#24000
b1011000 '
b1011000 !
b1011000 .
b1111000 /
b111000 &
b111000 -
b11111111111111111111111111111000 *
b11000 +
#25000
b1011001 '
b1011001 !
b1011001 .
b1111001 /
b111001 &
b111001 -
b11111111111111111111111111111001 *
b11001 +
#26000
b1011010 '
b1011010 !
b1011010 .
b1111010 /
b111010 &
b111010 -
b11111111111111111111111111111010 *
b11010 +
#27000
b1011011 '
b1011011 !
b1011011 .
b1111011 /
b111011 &
b111011 -
b11111111111111111111111111111011 *
b11011 +
#28000
b1011100 '
b1011100 !
b1011100 .
b1111100 /
b111100 &
b111100 -
b11111111111111111111111111111100 *
b11100 +
#29000
b1011101 '
b1011101 !
b1011101 .
b1111101 /
b111101 &
b111101 -
b11111111111111111111111111111101 *
b11101 +
#30000
b1011110 '
b1011110 !
b1011110 .
b1111110 /
b111110 &
b111110 -
b11111111111111111111111111111110 *
b11110 +
#31000
b1011111 '
b1011111 !
b1011111 .
b1111111 /
b111111 &
b111111 -
b11111111111111111111111111111111 *
b11111 +
#32000
b1100000 '
b1100000 !
b1100000 .
b0 /
b0 &
b0 -
b0 *
b100000 +
#33000
b1100001 '
b1100001 !
b1100001 .
b1 /
b1 &
b1 -
b1 *
b100001 +
#34000
b1100010 '
b1100010 !
b1100010 .
b10 /
b10 &
b10 -
b10 *
b100010 +
#35000
b1100011 '
b1100011 !
b1100011 .
b11 /
b11 &
b11 -
b11 *
b100011 +
#36000
b1100100 '
b1100100 !
b1100100 .
b100 /
b100 &
b100 -
b100 *
b100100 +
#37000
b1100101 '
b1100101 !
b1100101 .
b101 /
b101 &
b101 -
b101 *
b100101 +
#38000
b1100110 '
b1100110 !
b1100110 .
b110 /
b110 &
b110 -
b110 *
b100110 +
#39000
b1100111 '
b1100111 !
b1100111 .
b111 /
b111 &
b111 -
b111 *
b100111 +
#40000
b1101000 '
b1101000 !
b1101000 .
b1000 /
b1000 &
b1000 -
b1000 *
b101000 +
#41000
b1101001 '
b1101001 !
b1101001 .
b1001 /
b1001 &
b1001 -
b1001 *
b101001 +
#42000
b1101010 '
b1101010 !
b1101010 .
b1010 /
b1010 &
b1010 -
b1010 *
b101010 +
#43000
b1101011 '
b1101011 !
b1101011 .
b1011 /
b1011 &
b1011 -
b1011 *
b101011 +
#44000
b1101100 '
b1101100 !
b1101100 .
b1100 /
b1100 &
b1100 -
b1100 *
b101100 +
#45000
b1101101 '
b1101101 !
b1101101 .
b1101 /
b1101 &
b1101 -
b1101 *
b101101 +
#46000
b1101110 '
b1101110 !
b1101110 .
b1110 /
b1110 &
b1110 -
b1110 *
b101110 +
#47000
b1101111 '
b1101111 !
b1101111 .
b1111 /
b1111 &
b1111 -
b1111 *
b101111 +
#48000
b1110000 '
b1110000 !
b1110000 .
b10000 /
b10000 &
b10000 -
b10000 *
b110000 +
#49000
b1110001 '
b1110001 !
b1110001 .
b10001 /
b10001 &
b10001 -
b10001 *
b110001 +
#50000
b1110010 '
b1110010 !
b1110010 .
b10010 /
b10010 &
b10010 -
b10010 *
b110010 +
#51000
b1110011 '
b1110011 !
b1110011 .
b10011 /
b10011 &
b10011 -
b10011 *
b110011 +
#52000
b1110100 '
b1110100 !
b1110100 .
b10100 /
b10100 &
b10100 -
b10100 *
b110100 +
#53000
b1110101 '
b1110101 !
b1110101 .
b10101 /
b10101 &
b10101 -
b10101 *
b110101 +
#54000
b1110110 '
b1110110 !
b1110110 .
b10110 /
b10110 &
b10110 -
b10110 *
b110110 +
#55000
b1110111 '
b1110111 !
b1110111 .
b10111 /
b10111 &
b10111 -
b10111 *
b110111 +
#56000
b1111000 '
b1111000 !
b1111000 .
b11000 /
b11000 &
b11000 -
b11000 *
b111000 +
#57000
b1111001 '
b1111001 !
b1111001 .
b11001 /
b11001 &
b11001 -
b11001 *
b111001 +
#58000
b1111010 '
b1111010 !
b1111010 .
b11010 /
b11010 &
b11010 -
b11010 *
b111010 +
#59000
b1111011 '
b1111011 !
b1111011 .
b11011 /
b11011 &
b11011 -
b11011 *
b111011 +
#60000
b1111100 '
b1111100 !
b1111100 .
b11100 /
b11100 &
b11100 -
b11100 *
b111100 +
#61000
b1111101 '
b1111101 !
b1111101 .
b11101 /
b11101 &
b11101 -
b11101 *
b111101 +
#62000
b1111110 '
b1111110 !
b1111110 .
b11110 /
b11110 &
b11110 -
b11110 *
b111110 +
#63000
b1111111 '
b1111111 !
b1111111 .
b11111 /
b11111 &
b11111 -
b11111 *
b111111 +
#64000
b1000001 '
b1100000 /
b100000 &
b100000 -
b1000001 !
b1000001 .
b1100001 0
b100001 %
b100001 ,
b11111111111111111111111111100001 )
b11111111111111111111111111100000 *
b1000000 +
#65000
b1000010 '
b1000010 !
b1000010 .
b1100001 /
b100001 &
b100001 -
b11111111111111111111111111100001 *
b1000001 +
#66000
b1000011 '
b1000011 !
b1000011 .
b1100010 /
b100010 &
b100010 -
b11111111111111111111111111100010 *
b1000010 +
#67000
b1000100 '
b1000100 !
b1000100 .
b1100011 /
b100011 &
b100011 -
b11111111111111111111111111100011 *
b1000011 +
#68000
b1000101 '
b1000101 !
b1000101 .
b1100100 /
b100100 &
b100100 -
b11111111111111111111111111100100 *
b1000100 +
#69000
b1000110 '
b1000110 !
b1000110 .
b1100101 /
b100101 &
b100101 -
b11111111111111111111111111100101 *
b1000101 +
#70000
b1000111 '
b1000111 !
b1000111 .
b1100110 /
b100110 &
b100110 -
b11111111111111111111111111100110 *
b1000110 +
#71000
b1001000 '
b1001000 !
b1001000 .
b1100111 /
b100111 &
b100111 -
b11111111111111111111111111100111 *
b1000111 +
#72000
b1001001 '
b1001001 !
b1001001 .
b1101000 /
b101000 &
b101000 -
b11111111111111111111111111101000 *
b1001000 +
#73000
b1001010 '
b1001010 !
b1001010 .
b1101001 /
b101001 &
b101001 -
b11111111111111111111111111101001 *
b1001001 +
#74000
b1001011 '
b1001011 !
b1001011 .
b1101010 /
b101010 &
b101010 -
b11111111111111111111111111101010 *
b1001010 +
#75000
b1001100 '
b1001100 !
b1001100 .
b1101011 /
b101011 &
b101011 -
b11111111111111111111111111101011 *
b1001011 +
#76000
b1001101 '
b1001101 !
b1001101 .
b1101100 /
b101100 &
b101100 -
b11111111111111111111111111101100 *
b1001100 +
#77000
b1001110 '
b1001110 !
b1001110 .
b1101101 /
b101101 &
b101101 -
b11111111111111111111111111101101 *
b1001101 +
#78000
b1001111 '
b1001111 !
b1001111 .
b1101110 /
b101110 &
b101110 -
b11111111111111111111111111101110 *
b1001110 +
#79000
b1010000 '
b1010000 !
b1010000 .
b1101111 /
b101111 &
b101111 -
b11111111111111111111111111101111 *
b1001111 +
#80000
b1010001 '
b1010001 !
b1010001 .
b1110000 /
b110000 &
b110000 -
b11111111111111111111111111110000 *
b1010000 +
#81000
b1010010 '
b1010010 !
b1010010 .
b1110001 /
b110001 &
b110001 -
b11111111111111111111111111110001 *
b1010001 +
#82000
b1010011 '
b1010011 !
b1010011 .
b1110010 /
b110010 &
b110010 -
b11111111111111111111111111110010 *
b1010010 +
#83000
b1010100 '
b1010100 !
b1010100 .
b1110011 /
b110011 &
b110011 -
b11111111111111111111111111110011 *
b1010011 +
#84000
b1010101 '
b1010101 !
b1010101 .
b1110100 /
b110100 &
b110100 -
b11111111111111111111111111110100 *
b1010100 +
#85000
b1010110 '
b1010110 !
b1010110 .
b1110101 /
b110101 &
b110101 -
b11111111111111111111111111110101 *
b1010101 +
#86000
b1010111 '
b1010111 !
b1010111 .
b1110110 /
b110110 &
b110110 -
b11111111111111111111111111110110 *
b1010110 +
#87000
b1011000 '
b1011000 !
b1011000 .
b1110111 /
b110111 &
b110111 -
b11111111111111111111111111110111 *
b1010111 +
#88000
b1011001 '
b1011001 !
b1011001 .
b1111000 /
b111000 &
b111000 -
b11111111111111111111111111111000 *
b1011000 +
#89000
b1011010 '
b1011010 !
b1011010 .
b1111001 /
b111001 &
b111001 -
b11111111111111111111111111111001 *
b1011001 +
#90000
b1011011 '
b1011011 !
b1011011 .
b1111010 /
b111010 &
b111010 -
b11111111111111111111111111111010 *
b1011010 +
#91000
b1011100 '
b1011100 !
b1011100 .
b1111011 /
b111011 &
b111011 -
b11111111111111111111111111111011 *
b1011011 +
#92000
b1011101 '
b1011101 !
b1011101 .
b1111100 /
b111100 &
b111100 -
b11111111111111111111111111111100 *
b1011100 +
#93000
b1011110 '
b1011110 !
b1011110 .
b1111101 /
b111101 &
b111101 -
b11111111111111111111111111111101 *
b1011101 +
#94000
b1011111 '
b1011111 !
b1011111 .
b1111110 /
b111110 &
b111110 -
b11111111111111111111111111111110 *
b1011110 +
#95000
b1100000 '
b1100000 !
b1100000 .
b1111111 /
b111111 &
b111111 -
b11111111111111111111111111111111 *
b1011111 +
#96000
b1100001 '
b1100001 !
b1100001 .
b0 /
b0 &
b0 -
b0 *
b1100000 +
#97000
b1100010 '
b1100010 !
b1100010 .
b1 /
b1 &
b1 -
b1 *
b1100001 +
#98000
b1100011 '
b1100011 !
b1100011 .
b10 /
b10 &
b10 -
b10 *
b1100010 +
#99000
b1100100 '
b1100100 !
b1100100 .
b11 /
b11 &
b11 -
b11 *
b1100011 +
#100000
b1100101 '
b1100101 !
b1100101 .
b100 /
b100 &
b100 -
b100 *
b1100100 +
#101000
b1100110 '
b1100110 !
b1100110 .
b101 /
b101 &
b101 -
b101 *
b1100101 +
#102000
b1100111 '
b1100111 !
b1100111 .
b110 /
b110 &
b110 -
b110 *
b1100110 +
#103000
b1101000 '
b1101000 !
b1101000 .
b111 /
b111 &
b111 -
b111 *
b1100111 +
#104000
b1101001 '
b1101001 !
b1101001 .
b1000 /
b1000 &
b1000 -
b1000 *
b1101000 +
#105000
b1101010 '
b1101010 !
b1101010 .
b1001 /
b1001 &
b1001 -
b1001 *
b1101001 +
#106000
b1101011 '
b1101011 !
b1101011 .
b1010 /
b1010 &
b1010 -
b1010 *
b1101010 +
#107000
b1101100 '
b1101100 !
b1101100 .
b1011 /
b1011 &
b1011 -
b1011 *
b1101011 +
#108000
b1101101 '
b1101101 !
b1101101 .
b1100 /
b1100 &
b1100 -
b1100 *
b1101100 +
#109000
b1101110 '
b1101110 !
b1101110 .
b1101 /
b1101 &
b1101 -
b1101 *
b1101101 +
#110000
b1101111 '
b1101111 !
b1101111 .
b1110 /
b1110 &
b1110 -
b1110 *
b1101110 +
#111000
b1110000 '
b1110000 !
b1110000 .
b1111 /
b1111 &
b1111 -
b1111 *
b1101111 +
#112000
b1110001 '
b1110001 !
b1110001 .
b10000 /
b10000 &
b10000 -
b10000 *
b1110000 +
#113000
b1110010 '
b1110010 !
b1110010 .
b10001 /
b10001 &
b10001 -
b10001 *
b1110001 +
#114000
b1110011 '
b1110011 !
b1110011 .
b10010 /
b10010 &
b10010 -
b10010 *
b1110010 +
#115000
b1110100 '
b1110100 !
b1110100 .
b10011 /
b10011 &
b10011 -
b10011 *
b1110011 +
#116000
b1110101 '
b1110101 !
b1110101 .
b10100 /
b10100 &
b10100 -
b10100 *
b1110100 +
#117000
b1110110 '
b1110110 !
b1110110 .
b10101 /
b10101 &
b10101 -
b10101 *
b1110101 +
#118000
b1110111 '
b1110111 !
b1110111 .
b10110 /
b10110 &
b10110 -
b10110 *
b1110110 +
#119000
b1111000 '
b1111000 !
b1111000 .
b10111 /
b10111 &
b10111 -
b10111 *
b1110111 +
#120000
b1111001 '
b1111001 !
b1111001 .
b11000 /
b11000 &
b11000 -
b11000 *
b1111000 +
#121000
b1111010 '
b1111010 !
b1111010 .
b11001 /
b11001 &
b11001 -
b11001 *
b1111001 +
#122000
b1111011 '
b1111011 !
b1111011 .
b11010 /
b11010 &
b11010 -
b11010 *
b1111010 +
#123000
b1111100 '
b1111100 !
b1111100 .
b11011 /
b11011 &
b11011 -
b11011 *
b1111011 +
#124000
b1111101 '
b1111101 !
b1111101 .
b11100 /
b11100 &
b11100 -
b11100 *
b1111100 +
#125000
b1111110 '
b1111110 !
b1111110 .
b11101 /
b11101 &
b11101 -
b11101 *
b1111101 +
#126000
b1111111 '
b1111111 !
b1111111 .
b11110 /
b11110 &
b11110 -
b11110 *
b1111110 +
#127000
b0 '
b0 !
b0 .
b11111 /
b11111 &
b11111 -
b11111 *
b1111111 +
#128000
b1000010 '
b1100000 /
b100000 &
b100000 -
b1000010 !
b1000010 .
b1100010 0
b100010 %
b100010 ,
b11111111111111111111111111100010 )
b11111111111111111111111111100000 *
b10000000 +
#129000
b1000011 '
b1000011 !
b1000011 .
b1100001 /
b100001 &
b100001 -
b11111111111111111111111111100001 *
b10000001 +
#130000
b1000100 '
b1000100 !
b1000100 .
b1100010 /
b100010 &
b100010 -
b11111111111111111111111111100010 *
b10000010 +
#131000
b1000101 '
b1000101 !
b1000101 .
b1100011 /
b100011 &
b100011 -
b11111111111111111111111111100011 *
b10000011 +
#132000
b1000110 '
b1000110 !
b1000110 .
b1100100 /
b100100 &
b100100 -
b11111111111111111111111111100100 *
b10000100 +
#133000
b1000111 '
b1000111 !
b1000111 .
b1100101 /
b100101 &
b100101 -
b11111111111111111111111111100101 *
b10000101 +
#134000
b1001000 '
b1001000 !
b1001000 .
b1100110 /
b100110 &
b100110 -
b11111111111111111111111111100110 *
b10000110 +
#135000
b1001001 '
b1001001 !
b1001001 .
b1100111 /
b100111 &
b100111 -
b11111111111111111111111111100111 *
b10000111 +
#136000
b1001010 '
b1001010 !
b1001010 .
b1101000 /
b101000 &
b101000 -
b11111111111111111111111111101000 *
b10001000 +
#137000
b1001011 '
b1001011 !
b1001011 .
b1101001 /
b101001 &
b101001 -
b11111111111111111111111111101001 *
b10001001 +
#138000
b1001100 '
b1001100 !
b1001100 .
b1101010 /
b101010 &
b101010 -
b11111111111111111111111111101010 *
b10001010 +
#139000
b1001101 '
b1001101 !
b1001101 .
b1101011 /
b101011 &
b101011 -
b11111111111111111111111111101011 *
b10001011 +
#140000
b1001110 '
b1001110 !
b1001110 .
b1101100 /
b101100 &
b101100 -
b11111111111111111111111111101100 *
b10001100 +
#141000
b1001111 '
b1001111 !
b1001111 .
b1101101 /
b101101 &
b101101 -
b11111111111111111111111111101101 *
b10001101 +
#142000
b1010000 '
b1010000 !
b1010000 .
b1101110 /
b101110 &
b101110 -
b11111111111111111111111111101110 *
b10001110 +
#143000
b1010001 '
b1010001 !
b1010001 .
b1101111 /
b101111 &
b101111 -
b11111111111111111111111111101111 *
b10001111 +
#144000
b1010010 '
b1010010 !
b1010010 .
b1110000 /
b110000 &
b110000 -
b11111111111111111111111111110000 *
b10010000 +
#145000
b1010011 '
b1010011 !
b1010011 .
b1110001 /
b110001 &
b110001 -
b11111111111111111111111111110001 *
b10010001 +
#146000
b1010100 '
b1010100 !
b1010100 .
b1110010 /
b110010 &
b110010 -
b11111111111111111111111111110010 *
b10010010 +
#147000
b1010101 '
b1010101 !
b1010101 .
b1110011 /
b110011 &
b110011 -
b11111111111111111111111111110011 *
b10010011 +
#148000
b1010110 '
b1010110 !
b1010110 .
b1110100 /
b110100 &
b110100 -
b11111111111111111111111111110100 *
b10010100 +
#149000
b1010111 '
b1010111 !
b1010111 .
b1110101 /
b110101 &
b110101 -
b11111111111111111111111111110101 *
b10010101 +
#150000
b1011000 '
b1011000 !
b1011000 .
b1110110 /
b110110 &
b110110 -
b11111111111111111111111111110110 *
b10010110 +
#151000
b1011001 '
b1011001 !
b1011001 .
b1110111 /
b110111 &
b110111 -
b11111111111111111111111111110111 *
b10010111 +
#152000
b1011010 '
b1011010 !
b1011010 .
b1111000 /
b111000 &
b111000 -
b11111111111111111111111111111000 *
b10011000 +
#153000
b1011011 '
b1011011 !
b1011011 .
b1111001 /
b111001 &
b111001 -
b11111111111111111111111111111001 *
b10011001 +
#154000
b1011100 '
b1011100 !
b1011100 .
b1111010 /
b111010 &
b111010 -
b11111111111111111111111111111010 *
b10011010 +
#155000
b1011101 '
b1011101 !
b1011101 .
b1111011 /
b111011 &
b111011 -
b11111111111111111111111111111011 *
b10011011 +
#156000
b1011110 '
b1011110 !
b1011110 .
b1111100 /
b111100 &
b111100 -
b11111111111111111111111111111100 *
b10011100 +
#157000
b1011111 '
b1011111 !
b1011111 .
b1111101 /
b111101 &
b111101 -
b11111111111111111111111111111101 *
b10011101 +
#158000
b1100000 '
b1100000 !
b1100000 .
b1111110 /
b111110 &
b111110 -
b11111111111111111111111111111110 *
b10011110 +
#159000
b1100001 '
b1100001 !
b1100001 .
b1111111 /
b111111 &
b111111 -
b11111111111111111111111111111111 *
b10011111 +
#160000
b1100010 '
b1100010 !
b1100010 .
b0 /
b0 &
b0 -
b0 *
b10100000 +
#161000
b1100011 '
b1100011 !
b1100011 .
b1 /
b1 &
b1 -
b1 *
b10100001 +
#162000
b1100100 '
b1100100 !
b1100100 .
b10 /
b10 &
b10 -
b10 *
b10100010 +
#163000
b1100101 '
b1100101 !
b1100101 .
b11 /
b11 &
b11 -
b11 *
b10100011 +
#164000
b1100110 '
b1100110 !
b1100110 .
b100 /
b100 &
b100 -
b100 *
b10100100 +
#165000
b1100111 '
b1100111 !
b1100111 .
b101 /
b101 &
b101 -
b101 *
b10100101 +
#166000
b1101000 '
b1101000 !
b1101000 .
b110 /
b110 &
b110 -
b110 *
b10100110 +
#167000
b1101001 '
b1101001 !
b1101001 .
b111 /
b111 &
b111 -
b111 *
b10100111 +
#168000
b1101010 '
b1101010 !
b1101010 .
b1000 /
b1000 &
b1000 -
b1000 *
b10101000 +
#169000
b1101011 '
b1101011 !
b1101011 .
b1001 /
b1001 &
b1001 -
b1001 *
b10101001 +
#170000
b1101100 '
b1101100 !
b1101100 .
b1010 /
b1010 &
b1010 -
b1010 *
b10101010 +
#171000
b1101101 '
b1101101 !
b1101101 .
b1011 /
b1011 &
b1011 -
b1011 *
b10101011 +
#172000
b1101110 '
b1101110 !
b1101110 .
b1100 /
b1100 &
b1100 -
b1100 *
b10101100 +
#173000
b1101111 '
b1101111 !
b1101111 .
b1101 /
b1101 &
b1101 -
b1101 *
b10101101 +
#174000
b1110000 '
b1110000 !
b1110000 .
b1110 /
b1110 &
b1110 -
b1110 *
b10101110 +
#175000
b1110001 '
b1110001 !
b1110001 .
b1111 /
b1111 &
b1111 -
b1111 *
b10101111 +
#176000
b1110010 '
b1110010 !
b1110010 .
b10000 /
b10000 &
b10000 -
b10000 *
b10110000 +
#177000
b1110011 '
b1110011 !
b1110011 .
b10001 /
b10001 &
b10001 -
b10001 *
b10110001 +
#178000
b1110100 '
b1110100 !
b1110100 .
b10010 /
b10010 &
b10010 -
b10010 *
b10110010 +
#179000
b1110101 '
b1110101 !
b1110101 .
b10011 /
b10011 &
b10011 -
b10011 *
b10110011 +
#180000
b1110110 '
b1110110 !
b1110110 .
b10100 /
b10100 &
b10100 -
b10100 *
b10110100 +
#181000
b1110111 '
b1110111 !
b1110111 .
b10101 /
b10101 &
b10101 -
b10101 *
b10110101 +
#182000
b1111000 '
b1111000 !
b1111000 .
b10110 /
b10110 &
b10110 -
b10110 *
b10110110 +
#183000
b1111001 '
b1111001 !
b1111001 .
b10111 /
b10111 &
b10111 -
b10111 *
b10110111 +
#184000
b1111010 '
b1111010 !
b1111010 .
b11000 /
b11000 &
b11000 -
b11000 *
b10111000 +
#185000
b1111011 '
b1111011 !
b1111011 .
b11001 /
b11001 &
b11001 -
b11001 *
b10111001 +
#186000
b1111100 '
b1111100 !
b1111100 .
b11010 /
b11010 &
b11010 -
b11010 *
b10111010 +
#187000
b1111101 '
b1111101 !
b1111101 .
b11011 /
b11011 &
b11011 -
b11011 *
b10111011 +
#188000
b1111110 '
b1111110 !
b1111110 .
b11100 /
b11100 &
b11100 -
b11100 *
b10111100 +
#189000
b1111111 '
b1111111 !
b1111111 .
b11101 /
b11101 &
b11101 -
b11101 *
b10111101 +
#190000
b0 '
b0 !
b0 .
b11110 /
b11110 &
b11110 -
b11110 *
b10111110 +
#191000
b1 '
b1 !
b1 .
b11111 /
b11111 &
b11111 -
b11111 *
b10111111 +
#192000
b1000011 '
b1100000 /
b100000 &
b100000 -
b1000011 !
b1000011 .
b1100011 0
b100011 %
b100011 ,
b11111111111111111111111111100011 )
b11111111111111111111111111100000 *
b11000000 +
#193000
b1000100 '
b1000100 !
b1000100 .
b1100001 /
b100001 &
b100001 -
b11111111111111111111111111100001 *
b11000001 +
#194000
b1000101 '
b1000101 !
b1000101 .
b1100010 /
b100010 &
b100010 -
b11111111111111111111111111100010 *
b11000010 +
#195000
b1000110 '
b1000110 !
b1000110 .
b1100011 /
b100011 &
b100011 -
b11111111111111111111111111100011 *
b11000011 +
#196000
b1000111 '
b1000111 !
b1000111 .
b1100100 /
b100100 &
b100100 -
b11111111111111111111111111100100 *
b11000100 +
#197000
b1001000 '
b1001000 !
b1001000 .
b1100101 /
b100101 &
b100101 -
b11111111111111111111111111100101 *
b11000101 +
#198000
b1001001 '
b1001001 !
b1001001 .
b1100110 /
b100110 &
b100110 -
b11111111111111111111111111100110 *
b11000110 +
#199000
b1001010 '
b1001010 !
b1001010 .
b1100111 /
b100111 &
b100111 -
b11111111111111111111111111100111 *
b11000111 +
#200000
b1001011 '
b1001011 !
b1001011 .
b1101000 /
b101000 &
b101000 -
b11111111111111111111111111101000 *
b11001000 +
#201000
b1001100 '
b1001100 !
b1001100 .
b1101001 /
b101001 &
b101001 -
b11111111111111111111111111101001 *
b11001001 +
#202000
b1001101 '
b1001101 !
b1001101 .
b1101010 /
b101010 &
b101010 -
b11111111111111111111111111101010 *
b11001010 +
#203000
b1001110 '
b1001110 !
b1001110 .
b1101011 /
b101011 &
b101011 -
b11111111111111111111111111101011 *
b11001011 +
#204000
b1001111 '
b1001111 !
b1001111 .
b1101100 /
b101100 &
b101100 -
b11111111111111111111111111101100 *
b11001100 +
#205000
b1010000 '
b1010000 !
b1010000 .
b1101101 /
b101101 &
b101101 -
b11111111111111111111111111101101 *
b11001101 +
#206000
b1010001 '
b1010001 !
b1010001 .
b1101110 /
b101110 &
b101110 -
b11111111111111111111111111101110 *
b11001110 +
#207000
b1010010 '
b1010010 !
b1010010 .
b1101111 /
b101111 &
b101111 -
b11111111111111111111111111101111 *
b11001111 +
#208000
b1010011 '
b1010011 !
b1010011 .
b1110000 /
b110000 &
b110000 -
b11111111111111111111111111110000 *
b11010000 +
#209000
b1010100 '
b1010100 !
b1010100 .
b1110001 /
b110001 &
b110001 -
b11111111111111111111111111110001 *
b11010001 +
#210000
b1010101 '
b1010101 !
b1010101 .
b1110010 /
b110010 &
b110010 -
b11111111111111111111111111110010 *
b11010010 +
#211000
b1010110 '
b1010110 !
b1010110 .
b1110011 /
b110011 &
b110011 -
b11111111111111111111111111110011 *
b11010011 +
#212000
b1010111 '
b1010111 !
b1010111 .
b1110100 /
b110100 &
b110100 -
b11111111111111111111111111110100 *
b11010100 +
#213000
b1011000 '
b1011000 !
b1011000 .
b1110101 /
b110101 &
b110101 -
b11111111111111111111111111110101 *
b11010101 +
#214000
b1011001 '
b1011001 !
b1011001 .
b1110110 /
b110110 &
b110110 -
b11111111111111111111111111110110 *
b11010110 +
#215000
b1011010 '
b1011010 !
b1011010 .
b1110111 /
b110111 &
b110111 -
b11111111111111111111111111110111 *
b11010111 +
#216000
b1011011 '
b1011011 !
b1011011 .
b1111000 /
b111000 &
b111000 -
b11111111111111111111111111111000 *
b11011000 +
#217000
b1011100 '
b1011100 !
b1011100 .
b1111001 /
b111001 &
b111001 -
b11111111111111111111111111111001 *
b11011001 +
#218000
b1011101 '
b1011101 !
b1011101 .
b1111010 /
b111010 &
b111010 -
b11111111111111111111111111111010 *
b11011010 +
#219000
b1011110 '
b1011110 !
b1011110 .
b1111011 /
b111011 &
b111011 -
b11111111111111111111111111111011 *
b11011011 +
#220000
b1011111 '
b1011111 !
b1011111 .
b1111100 /
b111100 &
b111100 -
b11111111111111111111111111111100 *
b11011100 +
